{
  "kind": "collectionType",
  "collectionName": "datas",
  "info": {
    "singularName": "dataa",
    "pluralName": "datas",
    "displayName": "Data",
    "description": ""
  },
  "options": {
    "draftAndPublish": true
  },
  "pluginOptions": {},
  "attributes": {
    "firstname": {
      "type": "string",
      "required": true
    },
    "lastname": {
      "type": "string",
      "required": true
    },
    "email": {
      "type": "email",
      "required": true
    },
    "number": {
      "type": "string",
      "required": true
    },
    "password": {
      "type": "string",
      "required": true
    }
  }
}
